ap_lib/__init__.py
ap_lib/control.py
ap_lib/getdata.py
ap_lib/getstats.py
ap_lib/unpack_data2.py
ap_lib/unpack_stats.py
atomprobe_lib/__init__.py
atomprobe_lib/control.py
atomprobe_lib/getdata.py
atomprobe_lib/getstats.py
atomprobe_lib/unpack_data2.py
atomprobe_lib/unpack_stats.py
atomprobe_lib-0.0.1.dist-info/METADATA
atomprobe_lib-0.0.1.dist-info/WHEEL
atomprobe_lib-0.0.1.dist-info/top_level.txt
atomprobe_lib-0.0.1.dist-info/RECORD
